somosweep/__init__.py
somosweep/_version.py
somosweep/batch_simulations.py
somosweep/generate_runs.py
somosweep/iter_utils.py
somosweep-0.1.5.dist-info/LICENSE
somosweep-0.1.5.dist-info/METADATA
somosweep-0.1.5.dist-info/WHEEL
somosweep-0.1.5.dist-info/top_level.txt
somosweep-0.1.5.dist-info/RECORD
