Metadata-Version: 2.1
Name: somosweep
Version: 0.1.5
Summary: A utility for running parameter sweeps in SoMo or SoMoGym.
Home-page: https://github.com/cbteeple/somosweep
Author: Clark B. Teeple
Author-email: cbteeple@gmail.com
License: MIT
Platform: UNKNOWN
Classifier: Development Status :: 1 - Planning
License-File: LICENSE
Requires-Dist: python-dateutil
Requires-Dist: six
Requires-Dist: natsort
Requires-Dist: pathos
